tests/__init__.py
tests/conftest.py
tests/test_code_generation_cpp.py
tests/test_code_generation_py.py
tests/utils.py
yuhe/__about__.py
yuhe/__init__.py
yuhe/__main__.py
yuhe/app.py
yuhe/code_generators.py
yuhe/config.py
yuhe/geometry_utils.py
yuhe/ui_utils.py
yuhe-0.0.3.dist-info/licenses/LICENSE
yuhe-0.0.3.dist-info/METADATA
yuhe-0.0.3.dist-info/WHEEL
yuhe-0.0.3.dist-info/entry_points.txt
yuhe-0.0.3.dist-info/top_level.txt
yuhe-0.0.3.dist-info/RECORD
